CHANGELOG.md
CMakeLists.txt
LICENSE
MANIFEST.in
README.md
SUPPORT.md
pyproject.toml
setup.py
Addons/CMakeLists.txt
Addons/TasmanianAddons.hpp
Addons/testAddons.cpp
Addons/testConstructSurrogate.hpp
Addons/testCustomTabulated.hpp
Addons/testExoticQuadrature.hpp
Addons/testLoadUnstructured.hpp
Addons/testMPI.cpp
Addons/testMPI.hpp
Addons/testMPIDream.hpp
Addons/tsgAddonsCommon.hpp
Addons/tsgCConstructSurrogate.cpp
Addons/tsgCExoticQuadrature.cpp
Addons/tsgCLoadNeededValues.cpp
Addons/tsgCLoadUnstructuredPoints.cpp
Addons/tsgCandidateManager.hpp
Addons/tsgConstructSurrogate.hpp
Addons/tsgExoticQuadrature.hpp
Addons/tsgLoadNeededValues.hpp
Addons/tsgLoadUnstructuredPoints.hpp
Addons/tsgMPIConstructGrid.hpp
Addons/tsgMPISampleDream.hpp
Addons/tsgMPIScatterDream.hpp
Addons/tsgMPIScatterGrid.hpp
Config/CMakeLists.examples.cmake
Config/Tasmanian.h
Config/Tasmanian.hpp
Config/TasmanianConfig.in.cmake
Config/TasmanianConfig.in.hpp
Config/TasmanianENVsetup.in.sh
Config/TasmanianMakefile.in
Config/magma_cmake.patch
Config/AltBuildSystems/HeaderConvert.py
Config/AltBuildSystems/TasmanianConfig.hpp
Config/AltBuildSystems/testConfigureData.py
Config/AltBuildSystems/tsgGetPaths.m
Config/CMakeIncludes/CMakeLists.txt
Config/CMakeIncludes/FindTasmanianDpcpp.cmake
Config/CMakeIncludes/FindTasmanianMagma.cmake
Config/CMakeIncludes/PythonImportTest.py
Config/CMakeIncludes/add_dependencies_target.cmake
Config/CMakeIncludes/all_examples.cmake
Config/CMakeIncludes/exports.cmake
Config/CMakeIncludes/helper_macros.cmake
Config/CMakeIncludes/master_targets.cmake
Config/CMakeIncludes/sanity_check_and_xsdk.cmake
Config/CMakeIncludes/setup_message.cmake
DREAM/CMakeLists.txt
DREAM/TasmanianDREAM.hpp
DREAM/dreamtest_main.cpp
DREAM/tasdreamExternalTests.cpp
DREAM/tasdreamExternalTests.hpp
DREAM/tsgDreamCorePDF.hpp
DREAM/tsgDreamCoreRandom.hpp
DREAM/tsgDreamEnumerates.hpp
DREAM/tsgDreamLikelihoodCore.hpp
DREAM/tsgDreamLikelyGaussian.cpp
DREAM/tsgDreamLikelyGaussian.hpp
DREAM/tsgDreamSample.hpp
Tasmanian.egg-info/PKG-INFO
Tasmanian.egg-info/SOURCES.txt
Tasmanian.egg-info/dependency_links.txt
Tasmanian.egg-info/requires.txt
Tasmanian.egg-info/top_level.txt
