Metadata-Version: 2.2
Name: Tasmanian
Version: 8.2
Summary: UQ library for sparse grids, optimization and Bayesian inference
Home-page: https://tasmanian.ornl.gov
Author: Miroslav Stoyanov
Author-email: stoyanovmk@ornl.gov
Classifier: Programming Language :: Python :: 3
Classifier: Programming Language :: C++
Classifier: Operating System :: OS Independent
License-File: LICENSE
Requires-Dist: numpy>=1.10
Dynamic: author
Dynamic: author-email
Dynamic: classifier
Dynamic: description
Dynamic: description-content-type
Dynamic: home-page
Dynamic: requires-dist
Dynamic: summary
